[
	{
		"name": "무호적 독립유공자 156인 정부, 대한민국 국적 부여",
		"url": "https://n.news.naver.com/mnews/article/022/0003714087?sid=100",
		"imgurl": "https://imgnews.pstatic.net/image/origin/056/2022/07/12/11300173.jpg?type=ofullfill106_72",
		"sec": "polictics"
	},
	{
		"name": "윤 대통령, 오늘 산자부·중기부 업무보고 청취…실행 전략 모색",
		"url": "https://n.news.naver.com/mnews/article/056/0011300173?sid=100",
		"imgurl": "https://imgnews.pstatic.net/image/origin/056/2022/07/12/11300172.jpg?type=ofullfill106_72",
		"sec": "polictics"
	},
	{
		"name": "여야 원내대표, 오늘 국회의장 주재 회동…원 구성 협상",
		"url": "https://n.news.naver.com/mnews/article/056/0011300172?sid=100",
		"imgurl": "https://imgnews.pstatic.net/image/origin/056/2022/07/12/11300171.jpg?type=ofullfill106_72",
		"sec": "polictics"
	},
	{
		"name": "국민의힘, 文 정부 겨냥 ‘국가안보문란 TF’ 오늘 첫 회의",
		"url": "https://n.news.naver.com/mnews/article/056/0011300171?sid=100",
		"imgurl": "https://imgnews.pstatic.net/image/origin/003/2022/07/12/11298174.jpg?type=ofullfill106_72",
		"sec": "polictics"
	},
	{
		"name": "尹 대통령 덕분에...'선택할 자유', 11년 만에 개정판",
		"url": "https://n.news.naver.com/mnews/article/003/0011298174?sid=100",
		"imgurl": "https://imgnews.pstatic.net/image/origin/015/2022/07/12/4722928.jpg?type=ofullfill106_72",
		"sec": "polictics"
	},
	{
		"name": "\"김건희, 경호원 데리고 버버리서 3000만원 쇼핑\" 팩트체크해 보니",
		"url": "https://n.news.naver.com/mnews/article/015/0004722928?sid=100",
		"imgurl": "https://imgnews.pstatic.net/image/origin/214/2022/07/12/1208366.jpg?type=ofullfill106_72",
		"sec": "polictics"
	},
	{
		"name": "산업부·중소벤처부, 윤 대통령에 업무보고",
		"url": "https://n.news.naver.com/mnews/article/214/0001208366?sid=100",
		"imgurl": "https://imgnews.pstatic.net/image/origin/421/2022/07/12/6210700.jpg?type=ofullfill106_72",
		"sec": "polictics"
	},
	{
		"name": "美재무장관, 첫 방한 때 LG사이언스파크 방문…\"공급망 협력 강조\"",
		"url": "https://n.news.naver.com/mnews/article/421/0006210700?sid=100",
		"imgurl": "https://imgnews.pstatic.net/image/origin/079/2022/07/12/3663066.jpg?type=ofullfill106_72",
		"sec": "polictics"
	},
	{
		"name": "대통령실, \"김건희, 주말 명품 쇼핑 '허위사실'··강력유감\"",
		"url": "https://n.news.naver.com/mnews/article/079/0003663066?sid=100",
		"imgurl": "https://imgnews.pstatic.net/image/origin/654/2022/07/12/14700.jpg?type=ofullfill106_72",
		"sec": "polictics"
	}
]